ctrader_sdk/__init__.py
ctrader_sdk/ctrader_sdk.py
ctrader_sdk-0.1.1.dist-info/LICENSE
ctrader_sdk-0.1.1.dist-info/METADATA
ctrader_sdk-0.1.1.dist-info/WHEEL
ctrader_sdk-0.1.1.dist-info/top_level.txt
ctrader_sdk-0.1.1.dist-info/RECORD
