Metadata-Version: 2.1
Name: ctrader-sdk
Version: 0.1.1
Summary: A Python package for interacting with the cTrader API for trading and data fetching.
Home-page: https://github.com/Nils-Lopez/ctrader-sdk
Author: Nils Lopez
Author-email: lopez.nils@doctopus.app
License: UNKNOWN
Platform: UNKNOWN
Classifier: Programming Language :: Python :: 3
Classifier: License :: OSI Approved :: MIT License
Classifier: Operating System :: OS Independent
Requires-Python: >=3.6
License-File: LICENSE
